kazoo_locks/__init__.py
kazoo_locks/connection.py
kazoo_locks/locks.py
kazoo_locks/middleware.py
kazoo_locks/test_runners.py
kazoo_locks/management/__init__.py
kazoo_locks/management/commands/__init__.py
kazoo_locks/management/commands/migrate_with_kazoo.py
kazoo_locks/multiprocessing/__init__.py
kazoo_locks/multiprocessing/hooks.py
kazoo_locks/tests/__init__.py
kazoo_locks/tests/test_commands.py
kazoo_locks/tests/test_connection.py
kazoo_locks/tests/test_lock.py
kazoo_locks/tests/utils.py
django_kazoo_locks-2.0.0.dist-info/LICENSE
django_kazoo_locks-2.0.0.dist-info/METADATA
django_kazoo_locks-2.0.0.dist-info/WHEEL
django_kazoo_locks-2.0.0.dist-info/top_level.txt
django_kazoo_locks-2.0.0.dist-info/RECORD
