Metadata-Version: 2.1
Name: django-kazoo-locks
Version: 2.0.0
Summary: Utils for using Zookeeper locks through kazoo in Django commands and views.
Author: IIIT
Author-email: github@iiit.pl
License: UNKNOWN
Platform: UNKNOWN
Classifier: Environment :: Web Environment
Classifier: Framework :: Django
Classifier: Intended Audience :: Developers
Classifier: Operating System :: OS Independent
Classifier: Programming Language :: Python
Classifier: Programming Language :: Python :: 3.6
Classifier: Programming Language :: Python :: 3.7
Classifier: Programming Language :: Python :: 3.8
Classifier: Programming Language :: Python :: 3.9
License-File: LICENSE
Requires-Dist: Django (<3.3,>=2.0)
Requires-Dist: kazoo (==2.8.0)
